{
    "Default":{
        "Dwarf":{
            "Warrior":{
                "Warrior1":7,
                "Warrior2":5,
                "Warrior3":4,
                "Warrior4":1,
                "Warrior5":1,
                "Dwarf_the_dog":1
            },
            "Picker":{
                "Picker1":4,
                "Picker2":5,
                "Picker3":4,
                "Picker4":4,
                "Picker5":1,
                "Picker6":1,
                "Machin":1
            },
            "Scout":{
                "Scout1":2,
                "Scout2":3
            },
            "Blaster":{
                "Blaster1":2
            }
        },
        "Enemy":{
            "Dirt":{
                "Dirt":18
            },
            "Treasure":{
                "Treasure":10
            },
            "Meetings":{
                "Rat":7,
                "Gobelin":4,
                "Orc":4,
                "Troll":3,
                "Dragon":3
            },
            "Special_treasure_monster":{
                "Big_spider":1,
                "Demon_of_the_depths":1
            }
        },
        "Bonus":{
            "Beer_of_bravery":{
                "Beer_of_bravery":2
            },            
            "Nawak_sword":{
                "Nawak_sword":1
            },
            "Old_pickaxe":{
                "Old_pickaxe":1
            }
        },
        "Treasure":{
            "End_mine":{
                "Behind_door":1,
                "Throne_room":1
            },
            "Special_treasure":{
                "Unique_rings":2,
                "Grödur_ghost":2,
                "Hearth_gold":1
            },
            "Trophy":{
                "Employee_of_the_month":1,
                "Exterminator":1
            }
        }
    }
}